fkg_utils/__init__.py
fkg_utils/fkon/__init__.py
fkg_utils/fkon/login/__init__.py
fkg_utils/fkon/login/access_token.py
fkg_utils/fkon/queue/__init__.py
fkg_utils/fkon/queue/publishing_queue.py
fkg_utils/utils/__init__.py
fkg_utils/utils/utils.py
fkg_utils-0.1.12.dist-info/METADATA
fkg_utils-0.1.12.dist-info/WHEEL
fkg_utils-0.1.12.dist-info/RECORD
